AUTHORS
MANIFEST.in
README
metadata.py
setup.py
contentblock/__init__.py
contentblock/admin.py
contentblock/models.py
contentblock/migrations/0001_initial.py
contentblock/migrations/__init__.py
contentblock/templatetags/__init__.py
contentblock/templatetags/contentblock_tags.py
django_contentblock.egg-info/PKG-INFO
django_contentblock.egg-info/SOURCES.txt
django_contentblock.egg-info/dependency_links.txt
django_contentblock.egg-info/not-zip-safe
django_contentblock.egg-info/requires.txt
django_contentblock.egg-info/top_level.txt