Metadata-Version: 1.0
Name: django-contentblock
Version: 0.1.1
Summary: A simple app that allows using Multilingual contentblock using Placeholders from django-cms
Home-page: http://github.com/divio/django-contentblock
Author: Divio GmbH
Author-email: developers@divio.ch
License: BSD
Platform: OS Independent
Classifier: Development Status :: 4 - Beta
Classifier: Framework :: Django
Classifier: Intended Audience :: Developers
Classifier: License :: OSI Approved :: BSD License
Classifier: Operating System :: OS Independent
Classifier: Programming Language :: Python
Classifier: Topic :: Internet :: WWW/HTTP
